yelp/__init__.py
yelp/fusion.py
ezapi_yelp-0.4.10.dist-info/LICENSE
ezapi_yelp-0.4.10.dist-info/METADATA
ezapi_yelp-0.4.10.dist-info/WHEEL
ezapi_yelp-0.4.10.dist-info/top_level.txt
ezapi_yelp-0.4.10.dist-info/RECORD
